{"fromDateTime":"2019-12-29T21:00:00.000Z","installationId":88,"paramName":"PM25","tillDateTime":"2019-12-29T22:00:00.000Z","value":20.57}
{"fromDateTime":"2019-12-29T21:00:00.000Z","installationId":88,"paramName":"PM10","tillDateTime":"2019-12-29T22:00:00.000Z","value":25.78}
{"fromDateTime":"2019-12-29T21:00:00.000Z","installationId":88,"paramName":"NO2","tillDateTime":"2019-12-29T22:00:00.000Z","value":22.7}
{"fromDateTime":"2019-12-29T21:00:00.000Z","installationId":88,"paramName":"O3","tillDateTime":"2019-12-29T22:00:00.000Z","value":36.0}
{"fromDateTime":"2019-12-29T21:00:00.000Z","installationId":88,"paramName":"SO2","tillDateTime":"2019-12-29T22:00:00.000Z","value":4.29}
{"fromDateTime":"2019-12-29T21:00:00.000Z","installationId":88,"paramName":"CO","tillDateTime":"2019-12-29T22:00:00.000Z","value":749.0}
{"fromDateTime":"2019-12-29T22:00:00.000Z","installationId":88,"paramName":"PM25","tillDateTime":"2019-12-29T23:00:00.000Z","value":21.26}
{"fromDateTime":"2019-12-29T22:00:00.000Z","installationId":88,"paramName":"PM10","tillDateTime":"2019-12-29T23:00:00.000Z","value":26.38}
{"fromDateTime":"2019-12-29T22:00:00.000Z","installationId":88,"paramName":"NO2","tillDateTime":"2019-12-29T23:00:00.000Z","value":15.5}
{"fromDateTime":"2019-12-29T22:00:00.000Z","installationId":88,"paramName":"O3","tillDateTime":"2019-12-29T23:00:00.000Z","value":42.0}
{"fromDateTime":"2019-12-29T22:00:00.000Z","installationId":88,"paramName":"SO2","tillDateTime":"2019-12-29T23:00:00.000Z","value":3.29}
{"fromDateTime":"2019-12-29T22:00:00.000Z","installationId":88,"paramName":"CO","tillDateTime":"2019-12-29T23:00:00.000Z","value":742.0}
{"fromDateTime":"2019-12-29T23:00:00.000Z","installationId":88,"paramName":"PM25","tillDateTime":"2019-12-30T00:00:00.000Z","value":22.24}
{"fromDateTime":"2019-12-29T23:00:00.000Z","installationId":88,"paramName":"PM10","tillDateTime":"2019-12-30T00:00:00.000Z","value":31.27}
{"fromDateTime":"2019-12-29T23:00:00.000Z","installationId":88,"paramName":"NO2","tillDateTime":"2019-12-30T00:00:00.000Z","value":18.5}
{"fromDateTime":"2019-12-29T23:00:00.000Z","installationId":88,"paramName":"O3","tillDateTime":"2019-12-30T00:00:00.000Z","value":39.0}
{"fromDateTime":"2019-12-29T23:00:00.000Z","installationId":88,"paramName":"SO2","tillDateTime":"2019-12-30T00:00:00.000Z","value":3.29}
{"fromDateTime":"2019-12-29T23:00:00.000Z","installationId":88,"paramName":"CO","tillDateTime":"2019-12-30T00:00:00.000Z","value":926.0}
{"fromDateTime":"2019-12-30T00:00:00.000Z","installationId":88,"paramName":"PM25","tillDateTime":"2019-12-30T01:00:00.000Z","value":25.35}
{"fromDateTime":"2019-12-30T00:00:00.000Z","installationId":88,"paramName":"PM10","tillDateTime":"2019-12-30T01:00:00.000Z","value":31.99}
{"fromDateTime":"2019-12-30T00:00:00.000Z","installationId":88,"paramName":"NO2","tillDateTime":"2019-12-30T01:00:00.000Z","value":19.2}
{"fromDateTime":"2019-12-30T00:00:00.000Z","installationId":88,"paramName":"O3","tillDateTime":"2019-12-30T01:00:00.000Z","value":35.0}
{"fromDateTime":"2019-12-30T00:00:00.000Z","installationId":88,"paramName":"SO2","tillDateTime":"2019-12-30T01:00:00.000Z","value":4.53}
{"fromDateTime":"2019-12-30T00:00:00.000Z","installationId":88,"paramName":"CO","tillDateTime":"2019-12-30T01:00:00.000Z","value":859.0}
{"fromDateTime":"2019-12-30T01:00:00.000Z","installationId":88,"paramName":"PM25","tillDateTime":"2019-12-30T02:00:00.000Z","value":23.42}
{"fromDateTime":"2019-12-30T01:00:00.000Z","installationId":88,"paramName":"PM10","tillDateTime":"2019-12-30T02:00:00.000Z","value":29.19}
{"fromDateTime":"2019-12-30T01:00:00.000Z","installationId":88,"paramName":"NO2","tillDateTime":"2019-12-30T02:00:00.000Z","value":16.0}
{"fromDateTime":"2019-12-30T01:00:00.000Z","installationId":88,"paramName":"O3","tillDateTime":"2019-12-30T02:00:00.000Z","value":39.0}
{"fromDateTime":"2019-12-30T01:00:00.000Z","installationId":88,"paramName":"SO2","tillDateTime":"2019-12-30T02:00:00.000Z","value":4.18}
{"fromDateTime":"2019-12-30T01:00:00.000Z","installationId":88,"paramName":"CO","tillDateTime":"2019-12-30T02:00:00.000Z","value":905.0}
{"fromDateTime":"2019-12-30T02:00:00.000Z","installationId":88,"paramName":"PM25","tillDateTime":"2019-12-30T03:00:00.000Z","value":25.13}
{"fromDateTime":"2019-12-30T02:00:00.000Z","installationId":88,"paramName":"PM10","tillDateTime":"2019-12-30T03:00:00.000Z","value":32.04}
{"fromDateTime":"2019-12-30T02:00:00.000Z","installationId":88,"paramName":"NO2","tillDateTime":"2019-12-30T03:00:00.000Z","value":16.4}
{"fromDateTime":"2019-12-30T02:00:00.000Z","installationId":88,"paramName":"O3","tillDateTime":"2019-12-30T03:00:00.000Z","value":39.0}
{"fromDateTime":"2019-12-30T02:00:00.000Z","installationId":88,"paramName":"SO2","tillDateTime":"2019-12-30T03:00:00.000Z","value":4.8}
{"fromDateTime":"2019-12-30T02:00:00.000Z","installationId":88,"paramName":"CO","tillDateTime":"2019-12-30T03:00:00.000Z","value":804.0}
{"fromDateTime":"2019-12-30T03:00:00.000Z","installationId":88,"paramName":"PM25","tillDateTime":"2019-12-30T04:00:00.000Z","value":24.14}
{"fromDateTime":"2019-12-30T03:00:00.000Z","installationId":88,"paramName":"PM10","tillDateTime":"2019-12-30T04:00:00.000Z","value":31.63}
{"fromDateTime":"2019-12-30T03:00:00.000Z","installationId":88,"paramName":"NO2","tillDateTime":"2019-12-30T04:00:00.000Z","value":19.6}
{"fromDateTime":"2019-12-30T03:00:00.000Z","installationId":88,"paramName":"O3","tillDateTime":"2019-12-30T04:00:00.000Z","value":35.0}
{"fromDateTime":"2019-12-30T03:00:00.000Z","installationId":88,"paramName":"SO2","tillDateTime":"2019-12-30T04:00:00.000Z","value":5.19}
{"fromDateTime":"2019-12-30T03:00:00.000Z","installationId":88,"paramName":"CO","tillDateTime":"2019-12-30T04:00:00.000Z","value":882.0}
{"fromDateTime":"2019-12-30T04:00:00.000Z","installationId":88,"paramName":"PM25","tillDateTime":"2019-12-30T05:00:00.000Z","value":25.79}
{"fromDateTime":"2019-12-30T04:00:00.000Z","installationId":88,"paramName":"PM10","tillDateTime":"2019-12-30T05:00:00.000Z","value":33.92}
{"fromDateTime":"2019-12-30T04:00:00.000Z","installationId":88,"paramName":"NO2","tillDateTime":"2019-12-30T05:00:00.000Z","value":27.4}
{"fromDateTime":"2019-12-30T04:00:00.000Z","installationId":88,"paramName":"O3","tillDateTime":"2019-12-30T05:00:00.000Z","value":25.0}
{"fromDateTime":"2019-12-30T04:00:00.000Z","installationId":88,"paramName":"SO2","tillDateTime":"2019-12-30T05:00:00.000Z","value":6.6}
{"fromDateTime":"2019-12-30T04:00:00.000Z","installationId":88,"paramName":"CO","tillDateTime":"2019-12-30T05:00:00.000Z","value":956.0}
{"fromDateTime":"2019-12-30T05:00:00.000Z","installationId":88,"paramName":"PM25","tillDateTime":"2019-12-30T06:00:00.000Z","value":24.5}
{"fromDateTime":"2019-12-30T05:00:00.000Z","installationId":88,"paramName":"PM10","tillDateTime":"2019-12-30T06:00:00.000Z","value":33.19}
{"fromDateTime":"2019-12-30T05:00:00.000Z","installationId":88,"paramName":"NO2","tillDateTime":"2019-12-30T06:00:00.000Z","value":26.3}
{"fromDateTime":"2019-12-30T05:00:00.000Z","installationId":88,"paramName":"O3","tillDateTime":"2019-12-30T06:00:00.000Z","value":25.0}
{"fromDateTime":"2019-12-30T05:00:00.000Z","installationId":88,"paramName":"SO2","tillDateTime":"2019-12-30T06:00:00.000Z","value":7.38}
{"fromDateTime":"2019-12-30T05:00:00.000Z","installationId":88,"paramName":"CO","tillDateTime":"2019-12-30T06:00:00.000Z","value":889.0}
{"fromDateTime":"2019-12-30T06:00:00.000Z","installationId":88,"paramName":"PM25","tillDateTime":"2019-12-30T07:00:00.000Z","value":25.8}
{"fromDateTime":"2019-12-30T06:00:00.000Z","installationId":88,"paramName":"PM10","tillDateTime":"2019-12-30T07:00:00.000Z","value":34.01}
{"fromDateTime":"2019-12-30T06:00:00.000Z","installationId":88,"paramName":"NO2","tillDateTime":"2019-12-30T07:00:00.000Z","value":32.3}
{"fromDateTime":"2019-12-30T06:00:00.000Z","installationId":88,"paramName":"O3","tillDateTime":"2019-12-30T07:00:00.000Z","value":19.0}
{"fromDateTime":"2019-12-30T06:00:00.000Z","installationId":88,"paramName":"SO2","tillDateTime":"2019-12-30T07:00:00.000Z","value":8.15}
{"fromDateTime":"2019-12-30T06:00:00.000Z","installationId":88,"paramName":"CO","tillDateTime":"2019-12-30T07:00:00.000Z","value":915.0}
{"fromDateTime":"2019-12-30T07:00:00.000Z","installationId":88,"paramName":"PM25","tillDateTime":"2019-12-30T08:00:00.000Z","value":28.5}
{"fromDateTime":"2019-12-30T07:00:00.000Z","installationId":88,"paramName":"PM10","tillDateTime":"2019-12-30T08:00:00.000Z","value":36.29}
{"fromDateTime":"2019-12-30T07:00:00.000Z","installationId":88,"paramName":"NO2","tillDateTime":"2019-12-30T08:00:00.000Z","value":30.3}
{"fromDateTime":"2019-12-30T07:00:00.000Z","installationId":88,"paramName":"O3","tillDateTime":"2019-12-30T08:00:00.000Z","value":21.0}
{"fromDateTime":"2019-12-30T07:00:00.000Z","installationId":88,"paramName":"SO2","tillDateTime":"2019-12-30T08:00:00.000Z","value":9.33}
{"fromDateTime":"2019-12-30T07:00:00.000Z","installationId":88,"paramName":"CO","tillDateTime":"2019-12-30T08:00:00.000Z","value":899.0}
{"fromDateTime":"2019-12-30T08:00:00.000Z","installationId":88,"paramName":"PM25","tillDateTime":"2019-12-30T09:00:00.000Z","value":28.72}
{"fromDateTime":"2019-12-30T08:00:00.000Z","installationId":88,"paramName":"PM10","tillDateTime":"2019-12-30T09:00:00.000Z","value":36.1}
{"fromDateTime":"2019-12-30T08:00:00.000Z","installationId":88,"paramName":"NO2","tillDateTime":"2019-12-30T09:00:00.000Z","value":30.8}
{"fromDateTime":"2019-12-30T08:00:00.000Z","installationId":88,"paramName":"O3","tillDateTime":"2019-12-30T09:00:00.000Z","value":21.0}
{"fromDateTime":"2019-12-30T08:00:00.000Z","installationId":88,"paramName":"SO2","tillDateTime":"2019-12-30T09:00:00.000Z","value":9.54}
{"fromDateTime":"2019-12-30T08:00:00.000Z","installationId":88,"paramName":"CO","tillDateTime":"2019-12-30T09:00:00.000Z","value":893.0}
{"fromDateTime":"2019-12-30T09:00:00.000Z","installationId":88,"paramName":"PM25","tillDateTime":"2019-12-30T10:00:00.000Z","value":29.65}
{"fromDateTime":"2019-12-30T09:00:00.000Z","installationId":88,"paramName":"PM10","tillDateTime":"2019-12-30T10:00:00.000Z","value":38.63}
{"fromDateTime":"2019-12-30T09:00:00.000Z","installationId":88,"paramName":"NO2","tillDateTime":"2019-12-30T10:00:00.000Z","value":31.3}
{"fromDateTime":"2019-12-30T09:00:00.000Z","installationId":88,"paramName":"O3","tillDateTime":"2019-12-30T10:00:00.000Z","value":22.0}
{"fromDateTime":"2019-12-30T09:00:00.000Z","installationId":88,"paramName":"SO2","tillDateTime":"2019-12-30T10:00:00.000Z","value":10.29}
{"fromDateTime":"2019-12-30T09:00:00.000Z","installationId":88,"paramName":"CO","tillDateTime":"2019-12-30T10:00:00.000Z","value":890.0}
{"fromDateTime":"2019-12-30T10:00:00.000Z","installationId":88,"paramName":"PM25","tillDateTime":"2019-12-30T11:00:00.000Z","value":31.92}
{"fromDateTime":"2019-12-30T10:00:00.000Z","installationId":88,"paramName":"PM10","tillDateTime":"2019-12-30T11:00:00.000Z","value":46.15}
{"fromDateTime":"2019-12-30T10:00:00.000Z","installationId":88,"paramName":"NO2","tillDateTime":"2019-12-30T11:00:00.000Z","value":35.6}
{"fromDateTime":"2019-12-30T10:00:00.000Z","installationId":88,"paramName":"O3","tillDateTime":"2019-12-30T11:00:00.000Z","value":19.0}
{"fromDateTime":"2019-12-30T10:00:00.000Z","installationId":88,"paramName":"SO2","tillDateTime":"2019-12-30T11:00:00.000Z","value":10.25}
{"fromDateTime":"2019-12-30T10:00:00.000Z","installationId":88,"paramName":"CO","tillDateTime":"2019-12-30T11:00:00.000Z","value":993.0}
{"fromDateTime":"2019-12-30T11:00:00.000Z","installationId":88,"paramName":"PM25","tillDateTime":"2019-12-30T12:00:00.000Z","value":34.32}
{"fromDateTime":"2019-12-30T11:00:00.000Z","installationId":88,"paramName":"PM10","tillDateTime":"2019-12-30T12:00:00.000Z","value":49.9}
{"fromDateTime":"2019-12-30T11:00:00.000Z","installationId":88,"paramName":"NO2","tillDateTime":"2019-12-30T12:00:00.000Z","value":44.3}
{"fromDateTime":"2019-12-30T11:00:00.000Z","installationId":88,"paramName":"O3","tillDateTime":"2019-12-30T12:00:00.000Z","value":15.0}
{"fromDateTime":"2019-12-30T11:00:00.000Z","installationId":88,"paramName":"SO2","tillDateTime":"2019-12-30T12:00:00.000Z","value":12.36}
{"fromDateTime":"2019-12-30T11:00:00.000Z","installationId":88,"paramName":"CO","tillDateTime":"2019-12-30T12:00:00.000Z","value":1054.0}
{"fromDateTime":"2019-12-30T12:00:00.000Z","installationId":88,"paramName":"PM25","tillDateTime":"2019-12-30T13:00:00.000Z","value":33.66}
{"fromDateTime":"2019-12-30T12:00:00.000Z","installationId":88,"paramName":"PM10","tillDateTime":"2019-12-30T13:00:00.000Z","value":50.13}
{"fromDateTime":"2019-12-30T12:00:00.000Z","installationId":88,"paramName":"NO2","tillDateTime":"2019-12-30T13:00:00.000Z","value":52.2}
{"fromDateTime":"2019-12-30T12:00:00.000Z","installationId":88,"paramName":"O3","tillDateTime":"2019-12-30T13:00:00.000Z","value":14.0}
{"fromDateTime":"2019-12-30T12:00:00.000Z","installationId":88,"paramName":"SO2","tillDateTime":"2019-12-30T13:00:00.000Z","value":14.78}
{"fromDateTime":"2019-12-30T12:00:00.000Z","installationId":88,"paramName":"CO","tillDateTime":"2019-12-30T13:00:00.000Z","value":988.0}
{"fromDateTime":"2019-12-30T13:00:00.000Z","installationId":88,"paramName":"PM25","tillDateTime":"2019-12-30T14:00:00.000Z","value":31.34}
{"fromDateTime":"2019-12-30T13:00:00.000Z","installationId":88,"paramName":"PM10","tillDateTime":"2019-12-30T14:00:00.000Z","value":46.82}
{"fromDateTime":"2019-12-30T13:00:00.000Z","installationId":88,"paramName":"NO2","tillDateTime":"2019-12-30T14:00:00.000Z","value":54.2}
{"fromDateTime":"2019-12-30T13:00:00.000Z","installationId":88,"paramName":"O3","tillDateTime":"2019-12-30T14:00:00.000Z","value":16.0}
{"fromDateTime":"2019-12-30T13:00:00.000Z","installationId":88,"paramName":"SO2","tillDateTime":"2019-12-30T14:00:00.000Z","value":14.52}
{"fromDateTime":"2019-12-30T13:00:00.000Z","installationId":88,"paramName":"CO","tillDateTime":"2019-12-30T14:00:00.000Z","value":989.0}
{"fromDateTime":"2019-12-30T14:00:00.000Z","installationId":88,"paramName":"PM25","tillDateTime":"2019-12-30T15:00:00.000Z","value":27.1}
{"fromDateTime":"2019-12-30T14:00:00.000Z","installationId":88,"paramName":"PM10","tillDateTime":"2019-12-30T15:00:00.000Z","value":42.63}
{"fromDateTime":"2019-12-30T14:00:00.000Z","installationId":88,"paramName":"NO2","tillDateTime":"2019-12-30T15:00:00.000Z","value":60.3}
{"fromDateTime":"2019-12-30T14:00:00.000Z","installationId":88,"paramName":"O3","tillDateTime":"2019-12-30T15:00:00.000Z","value":15.0}
{"fromDateTime":"2019-12-30T14:00:00.000Z","installationId":88,"paramName":"SO2","tillDateTime":"2019-12-30T15:00:00.000Z","value":13.24}
{"fromDateTime":"2019-12-30T14:00:00.000Z","installationId":88,"paramName":"CO","tillDateTime":"2019-12-30T15:00:00.000Z","value":1026.0}
{"fromDateTime":"2019-12-30T15:00:00.000Z","installationId":88,"paramName":"PM25","tillDateTime":"2019-12-30T16:00:00.000Z","value":28.11}
{"fromDateTime":"2019-12-30T15:00:00.000Z","installationId":88,"paramName":"PM10","tillDateTime":"2019-12-30T16:00:00.000Z","value":48.35}
{"fromDateTime":"2019-12-30T15:00:00.000Z","installationId":88,"paramName":"NO2","tillDateTime":"2019-12-30T16:00:00.000Z","value":66.1}
{"fromDateTime":"2019-12-30T15:00:00.000Z","installationId":88,"paramName":"O3","tillDateTime":"2019-12-30T16:00:00.000Z","value":12.0}
{"fromDateTime":"2019-12-30T15:00:00.000Z","installationId":88,"paramName":"SO2","tillDateTime":"2019-12-30T16:00:00.000Z","value":14.9}
{"fromDateTime":"2019-12-30T15:00:00.000Z","installationId":88,"paramName":"CO","tillDateTime":"2019-12-30T16:00:00.000Z","value":1042.0}
{"fromDateTime":"2019-12-30T16:00:00.000Z","installationId":88,"paramName":"PM25","tillDateTime":"2019-12-30T17:00:00.000Z","value":31.7}
{"fromDateTime":"2019-12-30T16:00:00.000Z","installationId":88,"paramName":"PM10","tillDateTime":"2019-12-30T17:00:00.000Z","value":46.26}
{"fromDateTime":"2019-12-30T16:00:00.000Z","installationId":88,"paramName":"NO2","tillDateTime":"2019-12-30T17:00:00.000Z","value":57.2}
{"fromDateTime":"2019-12-30T16:00:00.000Z","installationId":88,"paramName":"O3","tillDateTime":"2019-12-30T17:00:00.000Z","value":15.0}
{"fromDateTime":"2019-12-30T16:00:00.000Z","installationId":88,"paramName":"SO2","tillDateTime":"2019-12-30T17:00:00.000Z","value":15.87}
{"fromDateTime":"2019-12-30T16:00:00.000Z","installationId":88,"paramName":"CO","tillDateTime":"2019-12-30T17:00:00.000Z","value":1031.0}
{"fromDateTime":"2019-12-30T17:00:00.000Z","installationId":88,"paramName":"PM25","tillDateTime":"2019-12-30T18:00:00.000Z","value":33.47}
{"fromDateTime":"2019-12-30T17:00:00.000Z","installationId":88,"paramName":"PM10","tillDateTime":"2019-12-30T18:00:00.000Z","value":46.17}
{"fromDateTime":"2019-12-30T17:00:00.000Z","installationId":88,"paramName":"NO2","tillDateTime":"2019-12-30T18:00:00.000Z","value":58.0}
{"fromDateTime":"2019-12-30T17:00:00.000Z","installationId":88,"paramName":"O3","tillDateTime":"2019-12-30T18:00:00.000Z","value":13.0}
{"fromDateTime":"2019-12-30T17:00:00.000Z","installationId":88,"paramName":"SO2","tillDateTime":"2019-12-30T18:00:00.000Z","value":16.19}
{"fromDateTime":"2019-12-30T17:00:00.000Z","installationId":88,"paramName":"CO","tillDateTime":"2019-12-30T18:00:00.000Z","value":1072.0}
{"fromDateTime":"2019-12-30T18:00:00.000Z","installationId":88,"paramName":"PM25","tillDateTime":"2019-12-30T19:00:00.000Z","value":30.45}
{"fromDateTime":"2019-12-30T18:00:00.000Z","installationId":88,"paramName":"PM10","tillDateTime":"2019-12-30T19:00:00.000Z","value":41.54}
{"fromDateTime":"2019-12-30T18:00:00.000Z","installationId":88,"paramName":"NO2","tillDateTime":"2019-12-30T19:00:00.000Z","value":52.0}
{"fromDateTime":"2019-12-30T18:00:00.000Z","installationId":88,"paramName":"O3","tillDateTime":"2019-12-30T19:00:00.000Z","value":19.0}
{"fromDateTime":"2019-12-30T18:00:00.000Z","installationId":88,"paramName":"SO2","tillDateTime":"2019-12-30T19:00:00.000Z","value":16.91}
{"fromDateTime":"2019-12-30T18:00:00.000Z","installationId":88,"paramName":"CO","tillDateTime":"2019-12-30T19:00:00.000Z","value":1037.0}
{"fromDateTime":"2019-12-30T19:00:00.000Z","installationId":88,"paramName":"PM25","tillDateTime":"2019-12-30T20:00:00.000Z","value":26.59}
{"fromDateTime":"2019-12-30T19:00:00.000Z","installationId":88,"paramName":"PM10","tillDateTime":"2019-12-30T20:00:00.000Z","value":36.72}
{"fromDateTime":"2019-12-30T19:00:00.000Z","installationId":88,"paramName":"NO2","tillDateTime":"2019-12-30T20:00:00.000Z","value":39.0}
{"fromDateTime":"2019-12-30T19:00:00.000Z","installationId":88,"paramName":"O3","tillDateTime":"2019-12-30T20:00:00.000Z","value":27.0}
{"fromDateTime":"2019-12-30T19:00:00.000Z","installationId":88,"paramName":"SO2","tillDateTime":"2019-12-30T20:00:00.000Z","value":14.45}
{"fromDateTime":"2019-12-30T19:00:00.000Z","installationId":88,"paramName":"CO","tillDateTime":"2019-12-30T20:00:00.000Z","value":948.0}
{"fromDateTime":"2019-12-30T20:00:00.000Z","installationId":88,"paramName":"PM25","tillDateTime":"2019-12-30T21:00:00.000Z","value":27.48}
{"fromDateTime":"2019-12-30T20:00:00.000Z","installationId":88,"paramName":"PM10","tillDateTime":"2019-12-30T21:00:00.000Z","value":36.62}
{"fromDateTime":"2019-12-30T20:00:00.000Z","installationId":88,"paramName":"NO2","tillDateTime":"2019-12-30T21:00:00.000Z","value":41.2}
{"fromDateTime":"2019-12-30T20:00:00.000Z","installationId":88,"paramName":"O3","tillDateTime":"2019-12-30T21:00:00.000Z","value":24.0}
{"fromDateTime":"2019-12-30T20:00:00.000Z","installationId":88,"paramName":"SO2","tillDateTime":"2019-12-30T21:00:00.000Z","value":13.98}
{"fromDateTime":"2019-12-30T20:00:00.000Z","installationId":88,"paramName":"CO","tillDateTime":"2019-12-30T21:00:00.000Z","value":979.0}
