{"fromDateTime":"2020-01-16T14:00:00.000Z","installationId":2339,"paramName":"PM1","tillDateTime":"2020-01-16T15:00:00.000Z","value":42.1}
{"fromDateTime":"2020-01-16T14:00:00.000Z","installationId":2339,"paramName":"PM25","tillDateTime":"2020-01-16T15:00:00.000Z","value":67.75}
{"fromDateTime":"2020-01-16T14:00:00.000Z","installationId":2339,"paramName":"PM10","tillDateTime":"2020-01-16T15:00:00.000Z","value":103.54}
{"fromDateTime":"2020-01-16T14:00:00.000Z","installationId":2339,"paramName":"PRESSURE","tillDateTime":"2020-01-16T15:00:00.000Z","value":1032.15}
{"fromDateTime":"2020-01-16T14:00:00.000Z","installationId":2339,"paramName":"HUMIDITY","tillDateTime":"2020-01-16T15:00:00.000Z","value":78.55}
{"fromDateTime":"2020-01-16T14:00:00.000Z","installationId":2339,"paramName":"TEMPERATURE","tillDateTime":"2020-01-16T15:00:00.000Z","value":3.4}
{"fromDateTime":"2020-01-16T15:00:00.000Z","installationId":2339,"paramName":"PM1","tillDateTime":"2020-01-16T16:00:00.000Z","value":43.95}
{"fromDateTime":"2020-01-16T15:00:00.000Z","installationId":2339,"paramName":"PM25","tillDateTime":"2020-01-16T16:00:00.000Z","value":69.92}
{"fromDateTime":"2020-01-16T15:00:00.000Z","installationId":2339,"paramName":"PM10","tillDateTime":"2020-01-16T16:00:00.000Z","value":106.8}
{"fromDateTime":"2020-01-16T15:00:00.000Z","installationId":2339,"paramName":"PRESSURE","tillDateTime":"2020-01-16T16:00:00.000Z","value":1032.77}
{"fromDateTime":"2020-01-16T15:00:00.000Z","installationId":2339,"paramName":"HUMIDITY","tillDateTime":"2020-01-16T16:00:00.000Z","value":79.92}
{"fromDateTime":"2020-01-16T15:00:00.000Z","installationId":2339,"paramName":"TEMPERATURE","tillDateTime":"2020-01-16T16:00:00.000Z","value":3.08}
{"fromDateTime":"2020-01-16T16:00:00.000Z","installationId":2339,"paramName":"PM1","tillDateTime":"2020-01-16T17:00:00.000Z","value":50.95}
{"fromDateTime":"2020-01-16T16:00:00.000Z","installationId":2339,"paramName":"PM25","tillDateTime":"2020-01-16T17:00:00.000Z","value":80.22}
{"fromDateTime":"2020-01-16T16:00:00.000Z","installationId":2339,"paramName":"PM10","tillDateTime":"2020-01-16T17:00:00.000Z","value":120.26}
{"fromDateTime":"2020-01-16T16:00:00.000Z","installationId":2339,"paramName":"PRESSURE","tillDateTime":"2020-01-16T17:00:00.000Z","value":1033.39}
{"fromDateTime":"2020-01-16T16:00:00.000Z","installationId":2339,"paramName":"HUMIDITY","tillDateTime":"2020-01-16T17:00:00.000Z","value":80.83}
{"fromDateTime":"2020-01-16T16:00:00.000Z","installationId":2339,"paramName":"TEMPERATURE","tillDateTime":"2020-01-16T17:00:00.000Z","value":2.21}
{"fromDateTime":"2020-01-16T17:00:00.000Z","installationId":2339,"paramName":"PM1","tillDateTime":"2020-01-16T18:00:00.000Z","value":51.63}
{"fromDateTime":"2020-01-16T17:00:00.000Z","installationId":2339,"paramName":"PM25","tillDateTime":"2020-01-16T18:00:00.000Z","value":81.28}
{"fromDateTime":"2020-01-16T17:00:00.000Z","installationId":2339,"paramName":"PM10","tillDateTime":"2020-01-16T18:00:00.000Z","value":121.2}
{"fromDateTime":"2020-01-16T17:00:00.000Z","installationId":2339,"paramName":"PRESSURE","tillDateTime":"2020-01-16T18:00:00.000Z","value":1033.62}
{"fromDateTime":"2020-01-16T17:00:00.000Z","installationId":2339,"paramName":"HUMIDITY","tillDateTime":"2020-01-16T18:00:00.000Z","value":82.08}
{"fromDateTime":"2020-01-16T17:00:00.000Z","installationId":2339,"paramName":"TEMPERATURE","tillDateTime":"2020-01-16T18:00:00.000Z","value":1.71}
{"fromDateTime":"2020-01-16T18:00:00.000Z","installationId":2339,"paramName":"PM1","tillDateTime":"2020-01-16T19:00:00.000Z","value":72.25}
{"fromDateTime":"2020-01-16T18:00:00.000Z","installationId":2339,"paramName":"PM25","tillDateTime":"2020-01-16T19:00:00.000Z","value":115.7}
{"fromDateTime":"2020-01-16T18:00:00.000Z","installationId":2339,"paramName":"PM10","tillDateTime":"2020-01-16T19:00:00.000Z","value":171.62}
{"fromDateTime":"2020-01-16T18:00:00.000Z","installationId":2339,"paramName":"PRESSURE","tillDateTime":"2020-01-16T19:00:00.000Z","value":1033.89}
{"fromDateTime":"2020-01-16T18:00:00.000Z","installationId":2339,"paramName":"HUMIDITY","tillDateTime":"2020-01-16T19:00:00.000Z","value":83.08}
{"fromDateTime":"2020-01-16T18:00:00.000Z","installationId":2339,"paramName":"TEMPERATURE","tillDateTime":"2020-01-16T19:00:00.000Z","value":1.03}
{"fromDateTime":"2020-01-16T19:00:00.000Z","installationId":2339,"paramName":"PM1","tillDateTime":"2020-01-16T20:00:00.000Z","value":86.76}
{"fromDateTime":"2020-01-16T19:00:00.000Z","installationId":2339,"paramName":"PM25","tillDateTime":"2020-01-16T20:00:00.000Z","value":140.3}
{"fromDateTime":"2020-01-16T19:00:00.000Z","installationId":2339,"paramName":"PM10","tillDateTime":"2020-01-16T20:00:00.000Z","value":209.79}
{"fromDateTime":"2020-01-16T19:00:00.000Z","installationId":2339,"paramName":"PRESSURE","tillDateTime":"2020-01-16T20:00:00.000Z","value":1033.85}
{"fromDateTime":"2020-01-16T19:00:00.000Z","installationId":2339,"paramName":"HUMIDITY","tillDateTime":"2020-01-16T20:00:00.000Z","value":85.75}
{"fromDateTime":"2020-01-16T19:00:00.000Z","installationId":2339,"paramName":"TEMPERATURE","tillDateTime":"2020-01-16T20:00:00.000Z","value":0.07}
{"fromDateTime":"2020-01-16T20:00:00.000Z","installationId":2339,"paramName":"PM1","tillDateTime":"2020-01-16T21:00:00.000Z","value":91.96}
{"fromDateTime":"2020-01-16T20:00:00.000Z","installationId":2339,"paramName":"PM25","tillDateTime":"2020-01-16T21:00:00.000Z","value":149.49}
{"fromDateTime":"2020-01-16T20:00:00.000Z","installationId":2339,"paramName":"PM10","tillDateTime":"2020-01-16T21:00:00.000Z","value":220.84}
{"fromDateTime":"2020-01-16T20:00:00.000Z","installationId":2339,"paramName":"PRESSURE","tillDateTime":"2020-01-16T21:00:00.000Z","value":1033.63}
{"fromDateTime":"2020-01-16T20:00:00.000Z","installationId":2339,"paramName":"HUMIDITY","tillDateTime":"2020-01-16T21:00:00.000Z","value":85.75}
{"fromDateTime":"2020-01-16T20:00:00.000Z","installationId":2339,"paramName":"TEMPERATURE","tillDateTime":"2020-01-16T21:00:00.000Z","value":-0.56}
{"fromDateTime":"2020-01-16T21:00:00.000Z","installationId":2339,"paramName":"PM1","tillDateTime":"2020-01-16T22:00:00.000Z","value":91.04}
{"fromDateTime":"2020-01-16T21:00:00.000Z","installationId":2339,"paramName":"PM25","tillDateTime":"2020-01-16T22:00:00.000Z","value":148.52}
{"fromDateTime":"2020-01-16T21:00:00.000Z","installationId":2339,"paramName":"PM10","tillDateTime":"2020-01-16T22:00:00.000Z","value":220.08}
{"fromDateTime":"2020-01-16T21:00:00.000Z","installationId":2339,"paramName":"PRESSURE","tillDateTime":"2020-01-16T22:00:00.000Z","value":1033.59}
{"fromDateTime":"2020-01-16T21:00:00.000Z","installationId":2339,"paramName":"HUMIDITY","tillDateTime":"2020-01-16T22:00:00.000Z","value":85.89}
{"fromDateTime":"2020-01-16T21:00:00.000Z","installationId":2339,"paramName":"TEMPERATURE","tillDateTime":"2020-01-16T22:00:00.000Z","value":-1.04}
{"fromDateTime":"2020-01-16T22:00:00.000Z","installationId":2339,"paramName":"PM1","tillDateTime":"2020-01-16T23:00:00.000Z","value":93.61}
{"fromDateTime":"2020-01-16T22:00:00.000Z","installationId":2339,"paramName":"PM25","tillDateTime":"2020-01-16T23:00:00.000Z","value":153.89}
{"fromDateTime":"2020-01-16T22:00:00.000Z","installationId":2339,"paramName":"PM10","tillDateTime":"2020-01-16T23:00:00.000Z","value":227.94}
{"fromDateTime":"2020-01-16T22:00:00.000Z","installationId":2339,"paramName":"PRESSURE","tillDateTime":"2020-01-16T23:00:00.000Z","value":1033.52}
{"fromDateTime":"2020-01-16T22:00:00.000Z","installationId":2339,"paramName":"HUMIDITY","tillDateTime":"2020-01-16T23:00:00.000Z","value":86.5}
{"fromDateTime":"2020-01-16T22:00:00.000Z","installationId":2339,"paramName":"TEMPERATURE","tillDateTime":"2020-01-16T23:00:00.000Z","value":-1.19}
{"fromDateTime":"2020-01-16T23:00:00.000Z","installationId":2339,"paramName":"PM1","tillDateTime":"2020-01-17T00:00:00.000Z","value":93.82}
{"fromDateTime":"2020-01-16T23:00:00.000Z","installationId":2339,"paramName":"PM25","tillDateTime":"2020-01-17T00:00:00.000Z","value":153.94}
{"fromDateTime":"2020-01-16T23:00:00.000Z","installationId":2339,"paramName":"PM10","tillDateTime":"2020-01-17T00:00:00.000Z","value":229.04}
{"fromDateTime":"2020-01-16T23:00:00.000Z","installationId":2339,"paramName":"PRESSURE","tillDateTime":"2020-01-17T00:00:00.000Z","value":1033.47}
{"fromDateTime":"2020-01-16T23:00:00.000Z","installationId":2339,"paramName":"HUMIDITY","tillDateTime":"2020-01-17T00:00:00.000Z","value":86.5}
{"fromDateTime":"2020-01-16T23:00:00.000Z","installationId":2339,"paramName":"TEMPERATURE","tillDateTime":"2020-01-17T00:00:00.000Z","value":-1.6}
{"fromDateTime":"2020-01-17T00:00:00.000Z","installationId":2339,"paramName":"PM1","tillDateTime":"2020-01-17T01:00:00.000Z","value":85.47}
{"fromDateTime":"2020-01-17T00:00:00.000Z","installationId":2339,"paramName":"PM25","tillDateTime":"2020-01-17T01:00:00.000Z","value":139.73}
{"fromDateTime":"2020-01-17T00:00:00.000Z","installationId":2339,"paramName":"PM10","tillDateTime":"2020-01-17T01:00:00.000Z","value":206.34}
{"fromDateTime":"2020-01-17T00:00:00.000Z","installationId":2339,"paramName":"PRESSURE","tillDateTime":"2020-01-17T01:00:00.000Z","value":1033.41}
{"fromDateTime":"2020-01-17T00:00:00.000Z","installationId":2339,"paramName":"HUMIDITY","tillDateTime":"2020-01-17T01:00:00.000Z","value":88.0}
{"fromDateTime":"2020-01-17T00:00:00.000Z","installationId":2339,"paramName":"TEMPERATURE","tillDateTime":"2020-01-17T01:00:00.000Z","value":-2.1}
{"fromDateTime":"2020-01-17T01:00:00.000Z","installationId":2339,"paramName":"PM1","tillDateTime":"2020-01-17T02:00:00.000Z","value":82.35}
{"fromDateTime":"2020-01-17T01:00:00.000Z","installationId":2339,"paramName":"PM25","tillDateTime":"2020-01-17T02:00:00.000Z","value":133.58}
{"fromDateTime":"2020-01-17T01:00:00.000Z","installationId":2339,"paramName":"PM10","tillDateTime":"2020-01-17T02:00:00.000Z","value":199.36}
{"fromDateTime":"2020-01-17T01:00:00.000Z","installationId":2339,"paramName":"PRESSURE","tillDateTime":"2020-01-17T02:00:00.000Z","value":1032.99}
{"fromDateTime":"2020-01-17T01:00:00.000Z","installationId":2339,"paramName":"HUMIDITY","tillDateTime":"2020-01-17T02:00:00.000Z","value":89.13}
{"fromDateTime":"2020-01-17T01:00:00.000Z","installationId":2339,"paramName":"TEMPERATURE","tillDateTime":"2020-01-17T02:00:00.000Z","value":-2.21}
{"fromDateTime":"2020-01-17T02:00:00.000Z","installationId":2339,"paramName":"PM1","tillDateTime":"2020-01-17T03:00:00.000Z","value":78.52}
{"fromDateTime":"2020-01-17T02:00:00.000Z","installationId":2339,"paramName":"PM25","tillDateTime":"2020-01-17T03:00:00.000Z","value":127.22}
{"fromDateTime":"2020-01-17T02:00:00.000Z","installationId":2339,"paramName":"PM10","tillDateTime":"2020-01-17T03:00:00.000Z","value":188.79}
{"fromDateTime":"2020-01-17T02:00:00.000Z","installationId":2339,"paramName":"PRESSURE","tillDateTime":"2020-01-17T03:00:00.000Z","value":1032.41}
{"fromDateTime":"2020-01-17T02:00:00.000Z","installationId":2339,"paramName":"HUMIDITY","tillDateTime":"2020-01-17T03:00:00.000Z","value":93.17}
{"fromDateTime":"2020-01-17T02:00:00.000Z","installationId":2339,"paramName":"TEMPERATURE","tillDateTime":"2020-01-17T03:00:00.000Z","value":-2.73}
{"fromDateTime":"2020-01-17T03:00:00.000Z","installationId":2339,"paramName":"PM1","tillDateTime":"2020-01-17T04:00:00.000Z","value":79.05}
{"fromDateTime":"2020-01-17T03:00:00.000Z","installationId":2339,"paramName":"PM25","tillDateTime":"2020-01-17T04:00:00.000Z","value":132.67}
{"fromDateTime":"2020-01-17T03:00:00.000Z","installationId":2339,"paramName":"PM10","tillDateTime":"2020-01-17T04:00:00.000Z","value":199.15}
{"fromDateTime":"2020-01-17T03:00:00.000Z","installationId":2339,"paramName":"PRESSURE","tillDateTime":"2020-01-17T04:00:00.000Z","value":1031.96}
{"fromDateTime":"2020-01-17T03:00:00.000Z","installationId":2339,"paramName":"HUMIDITY","tillDateTime":"2020-01-17T04:00:00.000Z","value":96.11}
{"fromDateTime":"2020-01-17T03:00:00.000Z","installationId":2339,"paramName":"TEMPERATURE","tillDateTime":"2020-01-17T04:00:00.000Z","value":-3.16}
{"fromDateTime":"2020-01-17T04:00:00.000Z","installationId":2339,"paramName":"PM1","tillDateTime":"2020-01-17T05:00:00.000Z","value":66.26}
{"fromDateTime":"2020-01-17T04:00:00.000Z","installationId":2339,"paramName":"PM25","tillDateTime":"2020-01-17T05:00:00.000Z","value":112.22}
{"fromDateTime":"2020-01-17T04:00:00.000Z","installationId":2339,"paramName":"PM10","tillDateTime":"2020-01-17T05:00:00.000Z","value":171.26}
{"fromDateTime":"2020-01-17T04:00:00.000Z","installationId":2339,"paramName":"PRESSURE","tillDateTime":"2020-01-17T05:00:00.000Z","value":1031.56}
{"fromDateTime":"2020-01-17T04:00:00.000Z","installationId":2339,"paramName":"HUMIDITY","tillDateTime":"2020-01-17T05:00:00.000Z","value":98.39}
{"fromDateTime":"2020-01-17T04:00:00.000Z","installationId":2339,"paramName":"TEMPERATURE","tillDateTime":"2020-01-17T05:00:00.000Z","value":-3.59}
{"fromDateTime":"2020-01-17T05:00:00.000Z","installationId":2339,"paramName":"PM1","tillDateTime":"2020-01-17T06:00:00.000Z","value":53.68}
{"fromDateTime":"2020-01-17T05:00:00.000Z","installationId":2339,"paramName":"PM25","tillDateTime":"2020-01-17T06:00:00.000Z","value":91.41}
{"fromDateTime":"2020-01-17T05:00:00.000Z","installationId":2339,"paramName":"PM10","tillDateTime":"2020-01-17T06:00:00.000Z","value":139.1}
{"fromDateTime":"2020-01-17T05:00:00.000Z","installationId":2339,"paramName":"PRESSURE","tillDateTime":"2020-01-17T06:00:00.000Z","value":1030.94}
{"fromDateTime":"2020-01-17T05:00:00.000Z","installationId":2339,"paramName":"HUMIDITY","tillDateTime":"2020-01-17T06:00:00.000Z","value":99.03}
{"fromDateTime":"2020-01-17T05:00:00.000Z","installationId":2339,"paramName":"TEMPERATURE","tillDateTime":"2020-01-17T06:00:00.000Z","value":-3.65}
{"fromDateTime":"2020-01-17T06:00:00.000Z","installationId":2339,"paramName":"PM1","tillDateTime":"2020-01-17T07:00:00.000Z","value":48.06}
{"fromDateTime":"2020-01-17T06:00:00.000Z","installationId":2339,"paramName":"PM25","tillDateTime":"2020-01-17T07:00:00.000Z","value":81.97}
{"fromDateTime":"2020-01-17T06:00:00.000Z","installationId":2339,"paramName":"PM10","tillDateTime":"2020-01-17T07:00:00.000Z","value":125.28}
{"fromDateTime":"2020-01-17T06:00:00.000Z","installationId":2339,"paramName":"PRESSURE","tillDateTime":"2020-01-17T07:00:00.000Z","value":1030.53}
{"fromDateTime":"2020-01-17T06:00:00.000Z","installationId":2339,"paramName":"HUMIDITY","tillDateTime":"2020-01-17T07:00:00.000Z","value":97.9}
{"fromDateTime":"2020-01-17T06:00:00.000Z","installationId":2339,"paramName":"TEMPERATURE","tillDateTime":"2020-01-17T07:00:00.000Z","value":-3.65}
{"fromDateTime":"2020-01-17T07:00:00.000Z","installationId":2339,"paramName":"PM1","tillDateTime":"2020-01-17T08:00:00.000Z","value":41.23}
{"fromDateTime":"2020-01-17T07:00:00.000Z","installationId":2339,"paramName":"PM25","tillDateTime":"2020-01-17T08:00:00.000Z","value":70.05}
{"fromDateTime":"2020-01-17T07:00:00.000Z","installationId":2339,"paramName":"PM10","tillDateTime":"2020-01-17T08:00:00.000Z","value":110.47}
{"fromDateTime":"2020-01-17T07:00:00.000Z","installationId":2339,"paramName":"PRESSURE","tillDateTime":"2020-01-17T08:00:00.000Z","value":1030.18}
{"fromDateTime":"2020-01-17T07:00:00.000Z","installationId":2339,"paramName":"HUMIDITY","tillDateTime":"2020-01-17T08:00:00.000Z","value":95.29}
{"fromDateTime":"2020-01-17T07:00:00.000Z","installationId":2339,"paramName":"TEMPERATURE","tillDateTime":"2020-01-17T08:00:00.000Z","value":-2.84}
{"fromDateTime":"2020-01-17T08:00:00.000Z","installationId":2339,"paramName":"PM1","tillDateTime":"2020-01-17T09:00:00.000Z","value":34.58}
{"fromDateTime":"2020-01-17T08:00:00.000Z","installationId":2339,"paramName":"PM25","tillDateTime":"2020-01-17T09:00:00.000Z","value":58.76}
{"fromDateTime":"2020-01-17T08:00:00.000Z","installationId":2339,"paramName":"PM10","tillDateTime":"2020-01-17T09:00:00.000Z","value":101.19}
{"fromDateTime":"2020-01-17T08:00:00.000Z","installationId":2339,"paramName":"PRESSURE","tillDateTime":"2020-01-17T09:00:00.000Z","value":1029.83}
{"fromDateTime":"2020-01-17T08:00:00.000Z","installationId":2339,"paramName":"HUMIDITY","tillDateTime":"2020-01-17T09:00:00.000Z","value":93.93}
{"fromDateTime":"2020-01-17T08:00:00.000Z","installationId":2339,"paramName":"TEMPERATURE","tillDateTime":"2020-01-17T09:00:00.000Z","value":-2.13}
{"fromDateTime":"2020-01-17T09:00:00.000Z","installationId":2339,"paramName":"PM1","tillDateTime":"2020-01-17T10:00:00.000Z","value":27.74}
{"fromDateTime":"2020-01-17T09:00:00.000Z","installationId":2339,"paramName":"PM25","tillDateTime":"2020-01-17T10:00:00.000Z","value":46.75}
{"fromDateTime":"2020-01-17T09:00:00.000Z","installationId":2339,"paramName":"PM10","tillDateTime":"2020-01-17T10:00:00.000Z","value":84.14}
{"fromDateTime":"2020-01-17T09:00:00.000Z","installationId":2339,"paramName":"PRESSURE","tillDateTime":"2020-01-17T10:00:00.000Z","value":1029.37}
{"fromDateTime":"2020-01-17T09:00:00.000Z","installationId":2339,"paramName":"HUMIDITY","tillDateTime":"2020-01-17T10:00:00.000Z","value":90.92}
{"fromDateTime":"2020-01-17T09:00:00.000Z","installationId":2339,"paramName":"TEMPERATURE","tillDateTime":"2020-01-17T10:00:00.000Z","value":-1.07}
{"fromDateTime":"2020-01-17T10:00:00.000Z","installationId":2339,"paramName":"PM1","tillDateTime":"2020-01-17T11:00:00.000Z","value":25.26}
{"fromDateTime":"2020-01-17T10:00:00.000Z","installationId":2339,"paramName":"PM25","tillDateTime":"2020-01-17T11:00:00.000Z","value":43.26}
{"fromDateTime":"2020-01-17T10:00:00.000Z","installationId":2339,"paramName":"PM10","tillDateTime":"2020-01-17T11:00:00.000Z","value":79.69}
{"fromDateTime":"2020-01-17T10:00:00.000Z","installationId":2339,"paramName":"PRESSURE","tillDateTime":"2020-01-17T11:00:00.000Z","value":1028.4}
{"fromDateTime":"2020-01-17T10:00:00.000Z","installationId":2339,"paramName":"HUMIDITY","tillDateTime":"2020-01-17T11:00:00.000Z","value":86.29}
{"fromDateTime":"2020-01-17T10:00:00.000Z","installationId":2339,"paramName":"TEMPERATURE","tillDateTime":"2020-01-17T11:00:00.000Z","value":0.92}
{"fromDateTime":"2020-01-17T11:00:00.000Z","installationId":2339,"paramName":"PM1","tillDateTime":"2020-01-17T12:00:00.000Z","value":25.24}
{"fromDateTime":"2020-01-17T11:00:00.000Z","installationId":2339,"paramName":"PM25","tillDateTime":"2020-01-17T12:00:00.000Z","value":42.92}
{"fromDateTime":"2020-01-17T11:00:00.000Z","installationId":2339,"paramName":"PM10","tillDateTime":"2020-01-17T12:00:00.000Z","value":79.65}
{"fromDateTime":"2020-01-17T11:00:00.000Z","installationId":2339,"paramName":"PRESSURE","tillDateTime":"2020-01-17T12:00:00.000Z","value":1027.28}
{"fromDateTime":"2020-01-17T11:00:00.000Z","installationId":2339,"paramName":"HUMIDITY","tillDateTime":"2020-01-17T12:00:00.000Z","value":80.36}
{"fromDateTime":"2020-01-17T11:00:00.000Z","installationId":2339,"paramName":"TEMPERATURE","tillDateTime":"2020-01-17T12:00:00.000Z","value":2.36}
{"fromDateTime":"2020-01-17T12:00:00.000Z","installationId":2339,"paramName":"PM1","tillDateTime":"2020-01-17T13:00:00.000Z","value":24.82}
{"fromDateTime":"2020-01-17T12:00:00.000Z","installationId":2339,"paramName":"PM25","tillDateTime":"2020-01-17T13:00:00.000Z","value":42.56}
{"fromDateTime":"2020-01-17T12:00:00.000Z","installationId":2339,"paramName":"PM10","tillDateTime":"2020-01-17T13:00:00.000Z","value":79.64}
{"fromDateTime":"2020-01-17T12:00:00.000Z","installationId":2339,"paramName":"PRESSURE","tillDateTime":"2020-01-17T13:00:00.000Z","value":1026.41}
{"fromDateTime":"2020-01-17T12:00:00.000Z","installationId":2339,"paramName":"HUMIDITY","tillDateTime":"2020-01-17T13:00:00.000Z","value":76.0}
{"fromDateTime":"2020-01-17T12:00:00.000Z","installationId":2339,"paramName":"TEMPERATURE","tillDateTime":"2020-01-17T13:00:00.000Z","value":3.41}
{"fromDateTime":"2020-01-17T13:00:00.000Z","installationId":2339,"paramName":"PM1","tillDateTime":"2020-01-17T14:00:00.000Z","value":23.67}
{"fromDateTime":"2020-01-17T13:00:00.000Z","installationId":2339,"paramName":"PM25","tillDateTime":"2020-01-17T14:00:00.000Z","value":39.9}
{"fromDateTime":"2020-01-17T13:00:00.000Z","installationId":2339,"paramName":"PM10","tillDateTime":"2020-01-17T14:00:00.000Z","value":74.48}
{"fromDateTime":"2020-01-17T13:00:00.000Z","installationId":2339,"paramName":"PRESSURE","tillDateTime":"2020-01-17T14:00:00.000Z","value":1025.48}
{"fromDateTime":"2020-01-17T13:00:00.000Z","installationId":2339,"paramName":"HUMIDITY","tillDateTime":"2020-01-17T14:00:00.000Z","value":73.0}
{"fromDateTime":"2020-01-17T13:00:00.000Z","installationId":2339,"paramName":"TEMPERATURE","tillDateTime":"2020-01-17T14:00:00.000Z","value":4.35}
