{"fromDateTime":"2020-03-30T15:00:00.000Z","hour":15,"installationId":2249,"paramName":"PM1","tillDateTime":"2020-03-30T16:00:00.000Z","value":10.13}
{"fromDateTime":"2020-03-30T15:00:00.000Z","hour":15,"installationId":2249,"paramName":"PM25","tillDateTime":"2020-03-30T16:00:00.000Z","value":15.12}
{"fromDateTime":"2020-03-30T15:00:00.000Z","hour":15,"installationId":2249,"paramName":"PM10","tillDateTime":"2020-03-30T16:00:00.000Z","value":22.0}
{"fromDateTime":"2020-03-30T15:00:00.000Z","hour":15,"installationId":2249,"paramName":"PRESSURE","tillDateTime":"2020-03-30T16:00:00.000Z","value":1023.62}
{"fromDateTime":"2020-03-30T15:00:00.000Z","hour":15,"installationId":2249,"paramName":"HUMIDITY","tillDateTime":"2020-03-30T16:00:00.000Z","value":38.42}
{"fromDateTime":"2020-03-30T15:00:00.000Z","hour":15,"installationId":2249,"paramName":"TEMPERATURE","tillDateTime":"2020-03-30T16:00:00.000Z","value":2.44}
{"fromDateTime":"2020-03-30T16:00:00.000Z","hour":16,"installationId":2249,"paramName":"PM1","tillDateTime":"2020-03-30T17:00:00.000Z","value":11.42}
{"fromDateTime":"2020-03-30T16:00:00.000Z","hour":16,"installationId":2249,"paramName":"PM25","tillDateTime":"2020-03-30T17:00:00.000Z","value":15.37}
{"fromDateTime":"2020-03-30T16:00:00.000Z","hour":16,"installationId":2249,"paramName":"PM10","tillDateTime":"2020-03-30T17:00:00.000Z","value":21.94}
{"fromDateTime":"2020-03-30T16:00:00.000Z","hour":16,"installationId":2249,"paramName":"PRESSURE","tillDateTime":"2020-03-30T17:00:00.000Z","value":1023.77}
{"fromDateTime":"2020-03-30T16:00:00.000Z","hour":16,"installationId":2249,"paramName":"HUMIDITY","tillDateTime":"2020-03-30T17:00:00.000Z","value":40.67}
{"fromDateTime":"2020-03-30T16:00:00.000Z","hour":16,"installationId":2249,"paramName":"TEMPERATURE","tillDateTime":"2020-03-30T17:00:00.000Z","value":1.86}
{"fromDateTime":"2020-03-30T17:00:00.000Z","hour":17,"installationId":2249,"paramName":"PM1","tillDateTime":"2020-03-30T18:00:00.000Z","value":9.5}
{"fromDateTime":"2020-03-30T17:00:00.000Z","hour":17,"installationId":2249,"paramName":"PM25","tillDateTime":"2020-03-30T18:00:00.000Z","value":12.92}
{"fromDateTime":"2020-03-30T17:00:00.000Z","hour":17,"installationId":2249,"paramName":"PM10","tillDateTime":"2020-03-30T18:00:00.000Z","value":18.4}
{"fromDateTime":"2020-03-30T17:00:00.000Z","hour":17,"installationId":2249,"paramName":"PRESSURE","tillDateTime":"2020-03-30T18:00:00.000Z","value":1024.03}
{"fromDateTime":"2020-03-30T17:00:00.000Z","hour":17,"installationId":2249,"paramName":"HUMIDITY","tillDateTime":"2020-03-30T18:00:00.000Z","value":44.36}
{"fromDateTime":"2020-03-30T17:00:00.000Z","hour":17,"installationId":2249,"paramName":"TEMPERATURE","tillDateTime":"2020-03-30T18:00:00.000Z","value":1.15}
{"fromDateTime":"2020-03-30T18:00:00.000Z","hour":18,"installationId":2249,"paramName":"PM1","tillDateTime":"2020-03-30T19:00:00.000Z","value":25.61}
{"fromDateTime":"2020-03-30T18:00:00.000Z","hour":18,"installationId":2249,"paramName":"PM25","tillDateTime":"2020-03-30T19:00:00.000Z","value":39.03}
{"fromDateTime":"2020-03-30T18:00:00.000Z","hour":18,"installationId":2249,"paramName":"PM10","tillDateTime":"2020-03-30T19:00:00.000Z","value":56.16}
{"fromDateTime":"2020-03-30T18:00:00.000Z","hour":18,"installationId":2249,"paramName":"PRESSURE","tillDateTime":"2020-03-30T19:00:00.000Z","value":1024.4}
{"fromDateTime":"2020-03-30T18:00:00.000Z","hour":18,"installationId":2249,"paramName":"HUMIDITY","tillDateTime":"2020-03-30T19:00:00.000Z","value":48.4}
{"fromDateTime":"2020-03-30T18:00:00.000Z","hour":18,"installationId":2249,"paramName":"TEMPERATURE","tillDateTime":"2020-03-30T19:00:00.000Z","value":0.4}
{"fromDateTime":"2020-03-30T19:00:00.000Z","hour":19,"installationId":2249,"paramName":"PM1","tillDateTime":"2020-03-30T20:00:00.000Z","value":28.83}
{"fromDateTime":"2020-03-30T19:00:00.000Z","hour":19,"installationId":2249,"paramName":"PM25","tillDateTime":"2020-03-30T20:00:00.000Z","value":43.96}
{"fromDateTime":"2020-03-30T19:00:00.000Z","hour":19,"installationId":2249,"paramName":"PM10","tillDateTime":"2020-03-30T20:00:00.000Z","value":63.15}
{"fromDateTime":"2020-03-30T19:00:00.000Z","hour":19,"installationId":2249,"paramName":"PRESSURE","tillDateTime":"2020-03-30T20:00:00.000Z","value":1024.58}
{"fromDateTime":"2020-03-30T19:00:00.000Z","hour":19,"installationId":2249,"paramName":"HUMIDITY","tillDateTime":"2020-03-30T20:00:00.000Z","value":53.88}
{"fromDateTime":"2020-03-30T19:00:00.000Z","hour":19,"installationId":2249,"paramName":"TEMPERATURE","tillDateTime":"2020-03-30T20:00:00.000Z","value":-0.27}
{"fromDateTime":"2020-03-30T20:00:00.000Z","hour":20,"installationId":2249,"paramName":"PM1","tillDateTime":"2020-03-30T21:00:00.000Z","value":30.74}
{"fromDateTime":"2020-03-30T20:00:00.000Z","hour":20,"installationId":2249,"paramName":"PM25","tillDateTime":"2020-03-30T21:00:00.000Z","value":46.95}
{"fromDateTime":"2020-03-30T20:00:00.000Z","hour":20,"installationId":2249,"paramName":"PM10","tillDateTime":"2020-03-30T21:00:00.000Z","value":67.3}
{"fromDateTime":"2020-03-30T20:00:00.000Z","hour":20,"installationId":2249,"paramName":"PRESSURE","tillDateTime":"2020-03-30T21:00:00.000Z","value":1024.82}
{"fromDateTime":"2020-03-30T20:00:00.000Z","hour":20,"installationId":2249,"paramName":"HUMIDITY","tillDateTime":"2020-03-30T21:00:00.000Z","value":56.85}
{"fromDateTime":"2020-03-30T20:00:00.000Z","hour":20,"installationId":2249,"paramName":"TEMPERATURE","tillDateTime":"2020-03-30T21:00:00.000Z","value":-0.99}
{"fromDateTime":"2020-03-30T21:00:00.000Z","hour":21,"installationId":2249,"paramName":"PM1","tillDateTime":"2020-03-30T22:00:00.000Z","value":24.26}
{"fromDateTime":"2020-03-30T21:00:00.000Z","hour":21,"installationId":2249,"paramName":"PM25","tillDateTime":"2020-03-30T22:00:00.000Z","value":36.77}
{"fromDateTime":"2020-03-30T21:00:00.000Z","hour":21,"installationId":2249,"paramName":"PM10","tillDateTime":"2020-03-30T22:00:00.000Z","value":52.49}
{"fromDateTime":"2020-03-30T21:00:00.000Z","hour":21,"installationId":2249,"paramName":"PRESSURE","tillDateTime":"2020-03-30T22:00:00.000Z","value":1024.96}
{"fromDateTime":"2020-03-30T21:00:00.000Z","hour":21,"installationId":2249,"paramName":"HUMIDITY","tillDateTime":"2020-03-30T22:00:00.000Z","value":63.23}
{"fromDateTime":"2020-03-30T21:00:00.000Z","hour":21,"installationId":2249,"paramName":"TEMPERATURE","tillDateTime":"2020-03-30T22:00:00.000Z","value":-1.37}
{"fromDateTime":"2020-03-30T22:00:00.000Z","hour":22,"installationId":2249,"paramName":"PM1","tillDateTime":"2020-03-30T23:00:00.000Z","value":24.75}
{"fromDateTime":"2020-03-30T22:00:00.000Z","hour":22,"installationId":2249,"paramName":"PM25","tillDateTime":"2020-03-30T23:00:00.000Z","value":38.03}
{"fromDateTime":"2020-03-30T22:00:00.000Z","hour":22,"installationId":2249,"paramName":"PM10","tillDateTime":"2020-03-30T23:00:00.000Z","value":54.57}
{"fromDateTime":"2020-03-30T22:00:00.000Z","hour":22,"installationId":2249,"paramName":"PRESSURE","tillDateTime":"2020-03-30T23:00:00.000Z","value":1024.97}
{"fromDateTime":"2020-03-30T22:00:00.000Z","hour":22,"installationId":2249,"paramName":"HUMIDITY","tillDateTime":"2020-03-30T23:00:00.000Z","value":65.53}
{"fromDateTime":"2020-03-30T22:00:00.000Z","hour":22,"installationId":2249,"paramName":"TEMPERATURE","tillDateTime":"2020-03-30T23:00:00.000Z","value":-1.68}
{"fromDateTime":"2020-03-30T23:00:00.000Z","hour":23,"installationId":2249,"paramName":"PM1","tillDateTime":"2020-03-31T00:00:00.000Z","value":30.78}
{"fromDateTime":"2020-03-30T23:00:00.000Z","hour":23,"installationId":2249,"paramName":"PM25","tillDateTime":"2020-03-31T00:00:00.000Z","value":47.72}
{"fromDateTime":"2020-03-30T23:00:00.000Z","hour":23,"installationId":2249,"paramName":"PM10","tillDateTime":"2020-03-31T00:00:00.000Z","value":68.89}
{"fromDateTime":"2020-03-30T23:00:00.000Z","hour":23,"installationId":2249,"paramName":"PRESSURE","tillDateTime":"2020-03-31T00:00:00.000Z","value":1024.96}
{"fromDateTime":"2020-03-30T23:00:00.000Z","hour":23,"installationId":2249,"paramName":"HUMIDITY","tillDateTime":"2020-03-31T00:00:00.000Z","value":68.14}
{"fromDateTime":"2020-03-30T23:00:00.000Z","hour":23,"installationId":2249,"paramName":"TEMPERATURE","tillDateTime":"2020-03-31T00:00:00.000Z","value":-1.91}
{"fromDateTime":"2020-03-31T00:00:00.000Z","hour":0,"installationId":2249,"paramName":"PM1","tillDateTime":"2020-03-31T01:00:00.000Z","value":31.47}
{"fromDateTime":"2020-03-31T00:00:00.000Z","hour":0,"installationId":2249,"paramName":"PM25","tillDateTime":"2020-03-31T01:00:00.000Z","value":48.69}
{"fromDateTime":"2020-03-31T00:00:00.000Z","hour":0,"installationId":2249,"paramName":"PM10","tillDateTime":"2020-03-31T01:00:00.000Z","value":70.43}
{"fromDateTime":"2020-03-31T00:00:00.000Z","hour":0,"installationId":2249,"paramName":"PRESSURE","tillDateTime":"2020-03-31T01:00:00.000Z","value":1024.84}
{"fromDateTime":"2020-03-31T00:00:00.000Z","hour":0,"installationId":2249,"paramName":"HUMIDITY","tillDateTime":"2020-03-31T01:00:00.000Z","value":71.84}
{"fromDateTime":"2020-03-31T00:00:00.000Z","hour":0,"installationId":2249,"paramName":"TEMPERATURE","tillDateTime":"2020-03-31T01:00:00.000Z","value":-2.08}
{"fromDateTime":"2020-03-31T01:00:00.000Z","hour":1,"installationId":2249,"paramName":"PM1","tillDateTime":"2020-03-31T02:00:00.000Z","value":32.34}
{"fromDateTime":"2020-03-31T01:00:00.000Z","hour":1,"installationId":2249,"paramName":"PM25","tillDateTime":"2020-03-31T02:00:00.000Z","value":49.64}
{"fromDateTime":"2020-03-31T01:00:00.000Z","hour":1,"installationId":2249,"paramName":"PM10","tillDateTime":"2020-03-31T02:00:00.000Z","value":71.9}
{"fromDateTime":"2020-03-31T01:00:00.000Z","hour":1,"installationId":2249,"paramName":"PRESSURE","tillDateTime":"2020-03-31T02:00:00.000Z","value":1024.72}
{"fromDateTime":"2020-03-31T01:00:00.000Z","hour":1,"installationId":2249,"paramName":"HUMIDITY","tillDateTime":"2020-03-31T02:00:00.000Z","value":74.59}
{"fromDateTime":"2020-03-31T01:00:00.000Z","hour":1,"installationId":2249,"paramName":"TEMPERATURE","tillDateTime":"2020-03-31T02:00:00.000Z","value":-2.56}
{"fromDateTime":"2020-03-31T02:00:00.000Z","hour":2,"installationId":2249,"paramName":"PM1","tillDateTime":"2020-03-31T03:00:00.000Z","value":34.62}
{"fromDateTime":"2020-03-31T02:00:00.000Z","hour":2,"installationId":2249,"paramName":"PM25","tillDateTime":"2020-03-31T03:00:00.000Z","value":54.11}
{"fromDateTime":"2020-03-31T02:00:00.000Z","hour":2,"installationId":2249,"paramName":"PM10","tillDateTime":"2020-03-31T03:00:00.000Z","value":78.59}
{"fromDateTime":"2020-03-31T02:00:00.000Z","hour":2,"installationId":2249,"paramName":"PRESSURE","tillDateTime":"2020-03-31T03:00:00.000Z","value":1024.75}
{"fromDateTime":"2020-03-31T02:00:00.000Z","hour":2,"installationId":2249,"paramName":"HUMIDITY","tillDateTime":"2020-03-31T03:00:00.000Z","value":77.56}
{"fromDateTime":"2020-03-31T02:00:00.000Z","hour":2,"installationId":2249,"paramName":"TEMPERATURE","tillDateTime":"2020-03-31T03:00:00.000Z","value":-3.01}
{"fromDateTime":"2020-03-31T03:00:00.000Z","hour":3,"installationId":2249,"paramName":"PM1","tillDateTime":"2020-03-31T04:00:00.000Z","value":35.54}
{"fromDateTime":"2020-03-31T03:00:00.000Z","hour":3,"installationId":2249,"paramName":"PM25","tillDateTime":"2020-03-31T04:00:00.000Z","value":53.89}
{"fromDateTime":"2020-03-31T03:00:00.000Z","hour":3,"installationId":2249,"paramName":"PM10","tillDateTime":"2020-03-31T04:00:00.000Z","value":77.18}
{"fromDateTime":"2020-03-31T03:00:00.000Z","hour":3,"installationId":2249,"paramName":"PRESSURE","tillDateTime":"2020-03-31T04:00:00.000Z","value":1024.82}
{"fromDateTime":"2020-03-31T03:00:00.000Z","hour":3,"installationId":2249,"paramName":"HUMIDITY","tillDateTime":"2020-03-31T04:00:00.000Z","value":78.25}
{"fromDateTime":"2020-03-31T03:00:00.000Z","hour":3,"installationId":2249,"paramName":"TEMPERATURE","tillDateTime":"2020-03-31T04:00:00.000Z","value":-3.35}
{"fromDateTime":"2020-03-31T04:00:00.000Z","hour":4,"installationId":2249,"paramName":"PM1","tillDateTime":"2020-03-31T05:00:00.000Z","value":33.55}
{"fromDateTime":"2020-03-31T04:00:00.000Z","hour":4,"installationId":2249,"paramName":"PM25","tillDateTime":"2020-03-31T05:00:00.000Z","value":50.56}
{"fromDateTime":"2020-03-31T04:00:00.000Z","hour":4,"installationId":2249,"paramName":"PM10","tillDateTime":"2020-03-31T05:00:00.000Z","value":72.14}
{"fromDateTime":"2020-03-31T04:00:00.000Z","hour":4,"installationId":2249,"paramName":"PRESSURE","tillDateTime":"2020-03-31T05:00:00.000Z","value":1025.16}
{"fromDateTime":"2020-03-31T04:00:00.000Z","hour":4,"installationId":2249,"paramName":"HUMIDITY","tillDateTime":"2020-03-31T05:00:00.000Z","value":78.57}
{"fromDateTime":"2020-03-31T04:00:00.000Z","hour":4,"installationId":2249,"paramName":"TEMPERATURE","tillDateTime":"2020-03-31T05:00:00.000Z","value":-3.21}
{"fromDateTime":"2020-03-31T05:00:00.000Z","hour":5,"installationId":2249,"paramName":"PM1","tillDateTime":"2020-03-31T06:00:00.000Z","value":35.18}
{"fromDateTime":"2020-03-31T05:00:00.000Z","hour":5,"installationId":2249,"paramName":"PM25","tillDateTime":"2020-03-31T06:00:00.000Z","value":53.28}
{"fromDateTime":"2020-03-31T05:00:00.000Z","hour":5,"installationId":2249,"paramName":"PM10","tillDateTime":"2020-03-31T06:00:00.000Z","value":76.3}
{"fromDateTime":"2020-03-31T05:00:00.000Z","hour":5,"installationId":2249,"paramName":"PRESSURE","tillDateTime":"2020-03-31T06:00:00.000Z","value":1025.83}
{"fromDateTime":"2020-03-31T05:00:00.000Z","hour":5,"installationId":2249,"paramName":"HUMIDITY","tillDateTime":"2020-03-31T06:00:00.000Z","value":78.47}
{"fromDateTime":"2020-03-31T05:00:00.000Z","hour":5,"installationId":2249,"paramName":"TEMPERATURE","tillDateTime":"2020-03-31T06:00:00.000Z","value":-3.0}
{"fromDateTime":"2020-03-31T06:00:00.000Z","hour":6,"installationId":2249,"paramName":"PM1","tillDateTime":"2020-03-31T07:00:00.000Z","value":31.25}
{"fromDateTime":"2020-03-31T06:00:00.000Z","hour":6,"installationId":2249,"paramName":"PM25","tillDateTime":"2020-03-31T07:00:00.000Z","value":46.86}
{"fromDateTime":"2020-03-31T06:00:00.000Z","hour":6,"installationId":2249,"paramName":"PM10","tillDateTime":"2020-03-31T07:00:00.000Z","value":67.35}
{"fromDateTime":"2020-03-31T06:00:00.000Z","hour":6,"installationId":2249,"paramName":"PRESSURE","tillDateTime":"2020-03-31T07:00:00.000Z","value":1026.22}
{"fromDateTime":"2020-03-31T06:00:00.000Z","hour":6,"installationId":2249,"paramName":"HUMIDITY","tillDateTime":"2020-03-31T07:00:00.000Z","value":75.58}
{"fromDateTime":"2020-03-31T06:00:00.000Z","hour":6,"installationId":2249,"paramName":"TEMPERATURE","tillDateTime":"2020-03-31T07:00:00.000Z","value":-2.17}
{"fromDateTime":"2020-03-31T07:00:00.000Z","hour":7,"installationId":2249,"paramName":"PM1","tillDateTime":"2020-03-31T08:00:00.000Z","value":22.72}
{"fromDateTime":"2020-03-31T07:00:00.000Z","hour":7,"installationId":2249,"paramName":"PM25","tillDateTime":"2020-03-31T08:00:00.000Z","value":32.71}
{"fromDateTime":"2020-03-31T07:00:00.000Z","hour":7,"installationId":2249,"paramName":"PM10","tillDateTime":"2020-03-31T08:00:00.000Z","value":47.89}
{"fromDateTime":"2020-03-31T07:00:00.000Z","hour":7,"installationId":2249,"paramName":"PRESSURE","tillDateTime":"2020-03-31T08:00:00.000Z","value":1026.56}
{"fromDateTime":"2020-03-31T07:00:00.000Z","hour":7,"installationId":2249,"paramName":"HUMIDITY","tillDateTime":"2020-03-31T08:00:00.000Z","value":68.54}
{"fromDateTime":"2020-03-31T07:00:00.000Z","hour":7,"installationId":2249,"paramName":"TEMPERATURE","tillDateTime":"2020-03-31T08:00:00.000Z","value":-0.65}
{"fromDateTime":"2020-03-31T08:00:00.000Z","hour":8,"installationId":2249,"paramName":"PM1","tillDateTime":"2020-03-31T09:00:00.000Z","value":20.95}
{"fromDateTime":"2020-03-31T08:00:00.000Z","hour":8,"installationId":2249,"paramName":"PM25","tillDateTime":"2020-03-31T09:00:00.000Z","value":29.72}
{"fromDateTime":"2020-03-31T08:00:00.000Z","hour":8,"installationId":2249,"paramName":"PM10","tillDateTime":"2020-03-31T09:00:00.000Z","value":43.36}
{"fromDateTime":"2020-03-31T08:00:00.000Z","hour":8,"installationId":2249,"paramName":"PRESSURE","tillDateTime":"2020-03-31T09:00:00.000Z","value":1026.76}
{"fromDateTime":"2020-03-31T08:00:00.000Z","hour":8,"installationId":2249,"paramName":"HUMIDITY","tillDateTime":"2020-03-31T09:00:00.000Z","value":62.68}
{"fromDateTime":"2020-03-31T08:00:00.000Z","hour":8,"installationId":2249,"paramName":"TEMPERATURE","tillDateTime":"2020-03-31T09:00:00.000Z","value":1.1}
{"fromDateTime":"2020-03-31T09:00:00.000Z","hour":9,"installationId":2249,"paramName":"PM1","tillDateTime":"2020-03-31T10:00:00.000Z","value":13.72}
{"fromDateTime":"2020-03-31T09:00:00.000Z","hour":9,"installationId":2249,"paramName":"PM25","tillDateTime":"2020-03-31T10:00:00.000Z","value":19.79}
{"fromDateTime":"2020-03-31T09:00:00.000Z","hour":9,"installationId":2249,"paramName":"PM10","tillDateTime":"2020-03-31T10:00:00.000Z","value":30.34}
{"fromDateTime":"2020-03-31T09:00:00.000Z","hour":9,"installationId":2249,"paramName":"PRESSURE","tillDateTime":"2020-03-31T10:00:00.000Z","value":1026.7}
{"fromDateTime":"2020-03-31T09:00:00.000Z","hour":9,"installationId":2249,"paramName":"HUMIDITY","tillDateTime":"2020-03-31T10:00:00.000Z","value":56.59}
{"fromDateTime":"2020-03-31T09:00:00.000Z","hour":9,"installationId":2249,"paramName":"TEMPERATURE","tillDateTime":"2020-03-31T10:00:00.000Z","value":2.81}
{"fromDateTime":"2020-03-31T10:00:00.000Z","hour":10,"installationId":2249,"paramName":"PM1","tillDateTime":"2020-03-31T11:00:00.000Z","value":12.19}
{"fromDateTime":"2020-03-31T10:00:00.000Z","hour":10,"installationId":2249,"paramName":"PM25","tillDateTime":"2020-03-31T11:00:00.000Z","value":17.11}
{"fromDateTime":"2020-03-31T10:00:00.000Z","hour":10,"installationId":2249,"paramName":"PM10","tillDateTime":"2020-03-31T11:00:00.000Z","value":24.68}
{"fromDateTime":"2020-03-31T10:00:00.000Z","hour":10,"installationId":2249,"paramName":"PRESSURE","tillDateTime":"2020-03-31T11:00:00.000Z","value":1026.52}
{"fromDateTime":"2020-03-31T10:00:00.000Z","hour":10,"installationId":2249,"paramName":"HUMIDITY","tillDateTime":"2020-03-31T11:00:00.000Z","value":53.77}
{"fromDateTime":"2020-03-31T10:00:00.000Z","hour":10,"installationId":2249,"paramName":"TEMPERATURE","tillDateTime":"2020-03-31T11:00:00.000Z","value":3.66}
{"fromDateTime":"2020-03-31T11:00:00.000Z","hour":11,"installationId":2249,"paramName":"PM1","tillDateTime":"2020-03-31T12:00:00.000Z","value":12.24}
{"fromDateTime":"2020-03-31T11:00:00.000Z","hour":11,"installationId":2249,"paramName":"PM25","tillDateTime":"2020-03-31T12:00:00.000Z","value":17.42}
{"fromDateTime":"2020-03-31T11:00:00.000Z","hour":11,"installationId":2249,"paramName":"PM10","tillDateTime":"2020-03-31T12:00:00.000Z","value":25.84}
{"fromDateTime":"2020-03-31T11:00:00.000Z","hour":11,"installationId":2249,"paramName":"PRESSURE","tillDateTime":"2020-03-31T12:00:00.000Z","value":1026.21}
{"fromDateTime":"2020-03-31T11:00:00.000Z","hour":11,"installationId":2249,"paramName":"HUMIDITY","tillDateTime":"2020-03-31T12:00:00.000Z","value":51.54}
{"fromDateTime":"2020-03-31T11:00:00.000Z","hour":11,"installationId":2249,"paramName":"TEMPERATURE","tillDateTime":"2020-03-31T12:00:00.000Z","value":3.69}
{"fromDateTime":"2020-03-31T12:00:00.000Z","hour":12,"installationId":2249,"paramName":"PM1","tillDateTime":"2020-03-31T13:00:00.000Z","value":13.61}
{"fromDateTime":"2020-03-31T12:00:00.000Z","hour":12,"installationId":2249,"paramName":"PM25","tillDateTime":"2020-03-31T13:00:00.000Z","value":19.15}
{"fromDateTime":"2020-03-31T12:00:00.000Z","hour":12,"installationId":2249,"paramName":"PM10","tillDateTime":"2020-03-31T13:00:00.000Z","value":28.07}
{"fromDateTime":"2020-03-31T12:00:00.000Z","hour":12,"installationId":2249,"paramName":"PRESSURE","tillDateTime":"2020-03-31T13:00:00.000Z","value":1025.84}
{"fromDateTime":"2020-03-31T12:00:00.000Z","hour":12,"installationId":2249,"paramName":"HUMIDITY","tillDateTime":"2020-03-31T13:00:00.000Z","value":48.29}
{"fromDateTime":"2020-03-31T12:00:00.000Z","hour":12,"installationId":2249,"paramName":"TEMPERATURE","tillDateTime":"2020-03-31T13:00:00.000Z","value":3.79}
{"fromDateTime":"2020-03-31T13:00:00.000Z","hour":13,"installationId":2249,"paramName":"PM1","tillDateTime":"2020-03-31T14:00:00.000Z","value":10.96}
{"fromDateTime":"2020-03-31T13:00:00.000Z","hour":13,"installationId":2249,"paramName":"PM25","tillDateTime":"2020-03-31T14:00:00.000Z","value":15.61}
{"fromDateTime":"2020-03-31T13:00:00.000Z","hour":13,"installationId":2249,"paramName":"PM10","tillDateTime":"2020-03-31T14:00:00.000Z","value":22.07}
{"fromDateTime":"2020-03-31T13:00:00.000Z","hour":13,"installationId":2249,"paramName":"PRESSURE","tillDateTime":"2020-03-31T14:00:00.000Z","value":1025.52}
{"fromDateTime":"2020-03-31T13:00:00.000Z","hour":13,"installationId":2249,"paramName":"HUMIDITY","tillDateTime":"2020-03-31T14:00:00.000Z","value":45.45}
{"fromDateTime":"2020-03-31T13:00:00.000Z","hour":13,"installationId":2249,"paramName":"TEMPERATURE","tillDateTime":"2020-03-31T14:00:00.000Z","value":4.36}
{"fromDateTime":"2020-03-31T14:00:00.000Z","hour":14,"installationId":2249,"paramName":"PM1","tillDateTime":"2020-03-31T15:00:00.000Z","value":11.14}
{"fromDateTime":"2020-03-31T14:00:00.000Z","hour":14,"installationId":2249,"paramName":"PM25","tillDateTime":"2020-03-31T15:00:00.000Z","value":15.9}
{"fromDateTime":"2020-03-31T14:00:00.000Z","hour":14,"installationId":2249,"paramName":"PM10","tillDateTime":"2020-03-31T15:00:00.000Z","value":22.66}
{"fromDateTime":"2020-03-31T14:00:00.000Z","hour":14,"installationId":2249,"paramName":"PRESSURE","tillDateTime":"2020-03-31T15:00:00.000Z","value":1025.6}
{"fromDateTime":"2020-03-31T14:00:00.000Z","hour":14,"installationId":2249,"paramName":"HUMIDITY","tillDateTime":"2020-03-31T15:00:00.000Z","value":47.98}
{"fromDateTime":"2020-03-31T14:00:00.000Z","hour":14,"installationId":2249,"paramName":"TEMPERATURE","tillDateTime":"2020-03-31T15:00:00.000Z","value":3.99}
